testouillos/main.py
testouillos-0.0.5.dist-info/WHEEL
testouillos-0.0.5.dist-info/METADATA
testouillos-0.0.5.dist-info/RECORD
